phc/__init__.py
phc/adapter.py
phc/api_response.py
phc/base_client.py
phc/easy/__init__.py
phc/easy/abstract/__init__.py
phc/easy/abstract/fhir_service_item.py
phc/easy/abstract/fhir_service_patient_item.py
phc/easy/abstract/genomic_variant.py
phc/easy/abstract/paging_api_item.py
phc/easy/audit_event.py
phc/easy/auth.py
phc/easy/care_plan.py
phc/easy/codeable.py
phc/easy/composition.py
phc/easy/condition.py
phc/easy/consent.py
phc/easy/diagnostic_report.py
phc/easy/document_reference.py
phc/easy/dstu3.py
phc/easy/encounter.py
phc/easy/frame.py
phc/easy/goal.py
phc/easy/imaging_study.py
phc/easy/immunization.py
phc/easy/media.py
phc/easy/medication_administration.py
phc/easy/medication_dispense.py
phc/easy/medication_request.py
phc/easy/medication_statement.py
phc/easy/observation.py
phc/easy/ocr/__init__.py
phc/easy/ocr/block.py
phc/easy/ocr/config.py
phc/easy/ocr/document.py
phc/easy/ocr/document_composition.py
phc/easy/ocr/options/__init__.py
phc/easy/ocr/options/ocr_config_types.py
phc/easy/ocr/suggestion.py
phc/easy/omics/__init__.py
phc/easy/omics/gene.py
phc/easy/omics/gene_set.py
phc/easy/omics/genomic_copy_number_variant.py
phc/easy/omics/genomic_expression.py
phc/easy/omics/genomic_short_variant.py
phc/easy/omics/genomic_structural_variant.py
phc/easy/omics/genomic_test.py
phc/easy/omics/options/__init__.py
phc/easy/omics/options/chromosome.py
phc/easy/omics/options/clinvar_review.py
phc/easy/omics/options/clinvar_significance.py
phc/easy/omics/options/coding_effect.py
phc/easy/omics/options/common.py
phc/easy/omics/options/copy_number_status.py
phc/easy/omics/options/gene_class.py
phc/easy/omics/options/genomic_copy_number_variant.py
phc/easy/omics/options/genomic_expression.py
phc/easy/omics/options/genomic_short_variant.py
phc/easy/omics/options/genomic_structural_variant.py
phc/easy/omics/options/genomic_test.py
phc/easy/omics/options/in_frame.py
phc/easy/omics/options/structural_type.py
phc/easy/omics/options/zygosity.py
phc/easy/option.py
phc_sdk_py-0.33.1.dist-info/LICENSE
phc_sdk_py-0.33.1.dist-info/METADATA
phc_sdk_py-0.33.1.dist-info/WHEEL
phc_sdk_py-0.33.1.dist-info/RECORD
